{
  "id": "c6002",
  "type": "cta",
  "content": [
    {
      "type": "section",
      "className": "cta-image-section",
      "style": {
        "position": "relative",
        "padding": "6rem 2rem",
        "backgroundImage": "url('https://images.unsplash.com/photo-1522071820081-009f0129c71c?ixlib=rb-4.0.3&ixid=MnwxMjA3fDB8MHxwaG90by1wYWdlfHx8fGVufDB8fHx8&auto=format&fit=crop&w=2070&q=80')",
        "backgroundSize": "cover",
        "backgroundPosition": "center",
        "backgroundAttachment": "fixed",
        "color": "#ffffff",
        "textAlign": "center"
      },
      "children": [
        {
          "type": "div",
          "className": "overlay",
          "style": {
            "position": "absolute",
            "top": 0,
            "left": 0,
            "width": "100%",
            "height": "100%",
            "backgroundColor": "rgba(0, 0, 0, 0.7)",
            "zIndex": 1
          }
        },
        {
          "type": "div",
          "className": "container",
          "style": {
            "maxWidth": "900px",
            "margin": "0 auto",
            "position": "relative",
            "zIndex": 2
          },
          "children": [
            {
              "type": "h2",
              "className": "cta-title",
              "content": "¿Listo para llevar tu negocio al siguiente nivel?",
              "style": {
                "fontSize": "3rem",
                "fontWeight": "bold",
                "marginBottom": "1.5rem",
                "textShadow": "2px 2px 4px rgba(0, 0, 0, 0.3)"
              }
            },
            {
              "type": "p",
              "className": "cta-description",
              "content": "Nuestro equipo de expertos está listo para ayudarte a crear una presencia digital impactante que convierta visitantes en clientes y potencie el crecimiento de tu negocio.",
              "style": {
                "fontSize": "1.25rem",
                "maxWidth": "800px",
                "margin": "0 auto 2.5rem",
                "lineHeight": 1.6,
                "textShadow": "1px 1px 2px rgba(0, 0, 0, 0.3)"
              }
            },
            {
              "type": "div",
              "className": "cta-buttons",
              "style": {
                "display": "flex",
                "justifyContent": "center",
                "gap": "1.5rem",
                "flexWrap": "wrap"
              },
              "children": [
                {
                  "type": "button",
                  "className": "cta-button-primary",
                  "content": "Solicitar una consulta gratuita",
                  "style": {
                    "backgroundColor": "#ff6b6b",
                    "color": "white",
                    "border": "none",
                    "padding": "1rem 2rem",
                    "fontSize": "1.1rem",
                    "borderRadius": "4px",
                    "cursor": "pointer",
                    "fontWeight": "bold",
                    "boxShadow": "0 4px 6px rgba(0, 0, 0, 0.1)",
                    "transition": "transform 0.3s ease, box-shadow 0.3s ease"
                  }
                },
                {
                  "type": "button",
                  "className": "cta-button-secondary",
                  "content": "Ver nuestro portafolio",
                  "style": {
                    "backgroundColor": "transparent",
                    "color": "white",
                    "border": "2px solid white",
                    "padding": "1rem 2rem",
                    "fontSize": "1.1rem",
                    "borderRadius": "4px",
                    "cursor": "pointer",
                    "fontWeight": "bold",
                    "boxShadow": "0 4px 6px rgba(0, 0, 0, 0.1)",
                    "transition": "background-color 0.3s, color 0.3s"
                  }
                }
              ]
            }
          ]
        }
      ]
    }
  ]
}
